aethermark/__init__.py
aethermark/__init__.pyi
aethermark/_core.cpython-39-x86_64-linux-gnu.so
aethermark.libs/libgcc_s-2298274a.so.1
aethermark.libs/libstdc++-08d5c7eb.so.6.0.33
aethermark-0.0.17.dist-info/METADATA
aethermark-0.0.17.dist-info/WHEEL
aethermark-0.0.17.dist-info/RECORD
aethermark-0.0.17.dist-info/licenses/LICENSE
