Metadata-Version: 2.1
Name: aethermark
Version: 0.0.17
Summary: Aethermark: A high-performance Markdown parser with AFM support.
Keywords: markdown,parser,pybind11,afm
Author-Email: Mukul Waval <mukulwaval@gmail.com>
Classifier: Development Status :: 1 - Planning
Classifier: License :: OSI Approved :: MIT License
Classifier: Programming Language :: Python :: 3
Classifier: Programming Language :: Python :: 3.10
Classifier: Programming Language :: C++
Classifier: Operating System :: OS Independent
Requires-Python: >=3.9
Provides-Extra: test
Requires-Dist: pytest; extra == "test"
